[
  {
    "id": 1,
    "name": "Adidas",
    "username": "Copa Sense.4 Fxg",
    "company": "36"
  },
  {
    "id": 2,
    "name": "Adidas",
    "username": "Copa Sense.4 Fxg",
    "company": "37"
  },
  {
    "id": 3,
    "name": "Adidas",
    "username": "Copa Sense.4 Fxg",
    "company": "38"
  },
  {
    "id": 4,
    "name": "Adidas",
    "username": "Copa Sense.4 Fxg",
    "company": "39"
  },
  {
    "id": 5,
    "name": "Adidas",
    "username": "Copa Sense.4 Fxg",
    "company": "40"
  },
  {
    "id": 6,
    "name": "Adidas",
    "username": "Copa Sense.4 Fxg",
    "company": "41"
  },
  {
    "id": 7,
    "name": "Adidas",
    "username": "Copa Sense.4 Fxg",
    "company": "42"
  },
  {
    "id": 8,
    "name": "Adidas",
    "username": "Copa Sense.4 Fxg",
    "company": "42.5"
  },
  {
    "id": 9,
    "name": "Adidas",
    "username": "Copa Sense.4 Fxg",
    "company": "43"
  },
  {
    "id": 10,
    "name": "Adidas",
    "username": "Copa Sense.4 Fxg",
    "company": "43.5"
  }


]